setup.py
s3clone/__init__.py
s3clone/humanize.py
s3clone/s3clone
s3clone.egg-info/PKG-INFO
s3clone.egg-info/SOURCES.txt
s3clone.egg-info/dependency_links.txt
s3clone.egg-info/requires.txt
s3clone.egg-info/top_level.txt