Metadata-Version: 1.0
Name: s3clone
Version: 1.0
Summary: Quickly download files from an S3 bucket
Home-page: https://github.com/pmitros/s3clone
Author: Piotr Mitros
Author-email: piotr@mitros.org
License: UNKNOWN
Platform: UNKNOWN
